mioXpektron/__init__.py
mioXpektron/pipeline.py
mioXpektron/py.typed
mioXpektron/.pytest_cache/README.md
mioXpektron/baseline/COLUMN_NAMING.md
mioXpektron/baseline/__init__.py
mioXpektron/baseline/baseline_base.py
mioXpektron/baseline/baseline_batch.py
mioXpektron/baseline/baseline_eval.py
mioXpektron/baseline/baseline_main.py
mioXpektron/baseline/flat_window_suggester.py
mioXpektron/baseline/test_column_aliases.py
mioXpektron/baseline/_deprecated/baseline_base_fast copy.py
mioXpektron/baseline/_deprecated/baseline_base_fast.py
mioXpektron/baseline/_deprecated/baseline_eval_fast copy.py
mioXpektron/baseline/_deprecated/baseline_eval_fast.py
mioXpektron/denoise/__init__.py
mioXpektron/denoise/denoise_batch.py
mioXpektron/denoise/denoise_doc.md
mioXpektron/denoise/denoise_main.py
mioXpektron/denoise/denoise_select.py
mioXpektron/denoise/main.py
mioXpektron/detection/__init__.py
mioXpektron/detection/check_overlapping_peaks.py
mioXpektron/detection/check_overlapping_peaks2.py
mioXpektron/detection/detection.py
mioXpektron/detection/peak_analysis.py
mioXpektron/normalization/__init__.py
mioXpektron/normalization/normalization.py
mioXpektron/normalization/preprocessing.py
mioXpektron/normalization/tic_count.py
mioXpektron/plotting/__init__.py
mioXpektron/plotting/plot.py
mioXpektron/plotting/plot_peaks.py
mioXpektron/recalibrate/DEBUG_README.md
mioXpektron/recalibrate/__init__.py
mioXpektron/recalibrate/auto_calibrator.py
mioXpektron/recalibrate/calibrate_spectrum.py
mioXpektron/recalibrate/flexible_calibrator.py
mioXpektron/recalibrate/flexible_calibrator_debug.py
mioXpektron/recalibrate/peak_picker.py
mioXpektron/recalibrate/peak_picker_uncal.py
mioXpektron/recalibrate/test_diagnostic.py
mioXpektron/recalibrate/_deprecated/FILE_CONSOLIDATION_COMPLETE.md
mioXpektron/recalibrate/_deprecated/README.md
mioXpektron/utils/__init__.py
mioXpektron/utils/analysis.py
mioXpektron/utils/file_management.py
mioXpektron/utils/main.py
mioxpektron-0.1.1.dist-info/licenses/LICENSE
mioxpektron-0.1.1.dist-info/METADATA
mioxpektron-0.1.1.dist-info/WHEEL
mioxpektron-0.1.1.dist-info/top_level.txt
mioxpektron-0.1.1.dist-info/RECORD
