Metadata-Version: 2.4
Name: mioXpektron
Version: 0.1.1
Summary: A comprehensive Time-of-Flight Secondary Ion Mass Spectrometry (ToF-SIMS) data processing toolkit
Author-email: Julhash Kazi <mioxpektron@kazilab.se>
License-Expression: MIT
Project-URL: Homepage, https://github.com/kazilab/mioXpektron
Project-URL: Documentation, https://github.com/kazilab/mioXpektron#readme
Project-URL: Repository, https://github.com/kazilab/mioXpektron
Project-URL: Issues, https://github.com/kazilab/mioXpektron/issues
Keywords: mass-spectrometry,tof-sims,signal-processing,denoising,baseline-correction,peak-detection,calibration,scientific-computing
Classifier: Development Status :: 4 - Beta
Classifier: Intended Audience :: Science/Research
Classifier: Topic :: Scientific/Engineering :: Chemistry
Classifier: Topic :: Scientific/Engineering :: Physics
Classifier: Programming Language :: Python :: 3
Classifier: Programming Language :: Python :: 3.8
Classifier: Programming Language :: Python :: 3.9
Classifier: Programming Language :: Python :: 3.10
Classifier: Programming Language :: Python :: 3.11
Classifier: Programming Language :: Python :: 3.12
Requires-Python: >=3.8
License-File: LICENSE
Requires-Dist: numpy>=1.20.0
Requires-Dist: pandas>=1.3.0
Requires-Dist: polars>=0.18.0
Requires-Dist: scipy>=1.7.0
Requires-Dist: matplotlib>=3.4.0
Requires-Dist: PyWavelets>=1.1.0
Requires-Dist: pybaselines>=1.0.0
Requires-Dist: scikit-learn>=1.0.0
Requires-Dist: joblib>=1.0.0
Requires-Dist: tqdm>=4.60.0
Provides-Extra: dev
Requires-Dist: pytest>=7.0; extra == "dev"
Requires-Dist: pytest-cov>=3.0; extra == "dev"
Requires-Dist: black>=22.0; extra == "dev"
Requires-Dist: isort>=5.0; extra == "dev"
Requires-Dist: mypy>=0.990; extra == "dev"
Requires-Dist: ruff>=0.1.0; extra == "dev"
Dynamic: license-file
